redbeard.py
redbeard_cli/__init__.py
redbeard_cli/file_utils.py
redbeard_cli/snowflake_utils.py
redbeard_cli/commands/__init__.py
redbeard_cli/commands/init/__init__.py
redbeard_cli/commands/init/clean_room_setup.py
redbeard_cli/commands/init/cli.py
redbeard_cli/commands/init/habu_setup.py
redbeard_cli/example/__init__.py
redbeard_cli/example/dataset.py
redbeard_cli/example/overlap_queries.py
redbeard_cli/sqlfiles/R__1init_habu_installer.sql
redbeard_cli/sqlfiles/R__create_new_cleanroom_udf.sql
redbeard_cli/sqlfiles/R__create_new_dataset.sql
redbeard_cli/sqlfiles/R__handle_error.sql
redbeard_cli/sqlfiles/R__handle_management_command.sql
redbeard_cli/sqlfiles/R__handle_new_cleanrooms.sql
redbeard_cli/sqlfiles/R__handle_warehouse_operations.sql
redbeard_cli/sqlfiles/R__init_habu_shares.sql
redbeard_cli/sqlfiles/R__new_data_connection.sql
redbeard_cli/sqlfiles/R__new_question_run.sql
redbeard_cli/sqlfiles/R__new_user_defined_function.sql
redbeard_cli/sqlfiles/R__post_run_query.sql
redbeard_cli/sqlfiles/R__process_request.sql
redbeard_cli/sqlfiles/R__question_run_accept_result_share.sql
redbeard_cli/sqlfiles/R__question_run_cleanup.sql
redbeard_cli/sqlfiles/R__question_run_data_share.sql
redbeard_cli/sqlfiles/R__question_run_result_share.sql
redbeard_cli/sqlfiles/R__setup_cleanroom_common.sql
redbeard_cli/sqlfiles/R__setup_data_connection_objects.sql
redbeard_cli/sqlfiles/R__setup_streams_tasks.sql
redbeard_cli/sqlfiles/R__sp_logger.sql
redbeard_cli/sqlfiles/V1_0_0_create.sql
redbeard_cli/sqlfiles/__init__.py
habu_snowflake_cli-5.1.0.dist-info/METADATA
habu_snowflake_cli-5.1.0.dist-info/WHEEL
habu_snowflake_cli-5.1.0.dist-info/entry_points.txt
habu_snowflake_cli-5.1.0.dist-info/top_level.txt
habu_snowflake_cli-5.1.0.dist-info/RECORD
