Metadata-Version: 2.4
Name: habu-snowflake-cli
Version: 5.1.0
Summary: Redbeard - Habu Snowflake CLI
Home-page: https://github.com/deklareddotcom/redbeard
Author: Habu Engineering
Author-email: engineering@habu.com
Requires-Python: >=3.7.10
Requires-Dist: python-dotenv~=1.0.0
Requires-Dist: click~=8.1.7
Requires-Dist: snowflake-connector-python~=3.10.0
Requires-Dist: pyyaml~=6.0
Dynamic: author
Dynamic: author-email
Dynamic: description
Dynamic: description-content-type
Dynamic: home-page
Dynamic: requires-dist
Dynamic: requires-python
Dynamic: summary
